Workbook

Sheet CA
N1: Verificação dos pesos
B2: Terreno | F2: Área Construída | I2: Relação entre aluguéis | N2: d | O2: =H30 -> 2 | P2: Peso relativo ao aluguel do Térreo
B3: Area | C3: 400 | D3: m2 | F3: Térreo | G3: 150 | H3: m2 | I3: d | J3: 2 | K3: (T x vezes mais caro!) | N3: p | O3: =(G15*G16*(O2-1)*(C6-C7)+C4*O2)/(C4-G15*G16*(O2-1)*C7) -> 2.5121951 | P3: Peso da Cota Parte para o Térreo
B4: qt | C4: 2000 | D4: R$/m2 | F4: Superiores | G4: 300 | H4: m2 | I4: p | J4: =(G20*(J3-1)*(C6-C7)+C4*J3)/(C4-G20*(J3-1)*C7) -> 2.5121951
B5: Vt | C5: =C3*C4 -> 800000 | D5: R$ | F5: Total | G5: =SUM(G3:G4) -> 450 | H5: m2
B6: CAbasico | C6: 1 | F6: Área Homogeneizada
B7: TO | C7: 0.5
F8: Idade Aparente | G8: Vida Útil | J8: Área Homogeneizada
F9: 10 | G9: 36 | I9: Pesos | J9: Existente | K9: Possível
F10: Vida Residual | G10: 0.2 | I10: =J4 -> 2.5121951 | J10: =I10*G3 -> 376.82927 | K10: =I10*C7*C3 -> 502.43902
I11: 1 | J11: =I11*G4 -> 300 | K11: =(C6-C7)*C3*I11 -> 200
B12: Aproveitamento do Terreo | F12: Benfeitoria | J12: =SUM(J10:J11) -> 676.82927 | K12: =SUM(K10:K11) -> 702.43902
B13: Ahe | C13: =J12 -> 676.82927 | F13: Coef. Padrao | G13: 1.5
B14: Ahp | C14: =K12 -> 702.43902 | F14: Custo Básico | G14: 500 | H14: R$/m2
B15: CA | C15: =C13/C14 -> 0.96354167 | F15: qb | G15: =G13*G14 -> 750 | H15: R$/m2
F16: Depreciação | G16: =G10+(1-G10)*(G9-F9)/G9 -> 0.77777778
B18: Capital Terreno | C18: =C15*C5 -> 770833.33 | F18: Capital Benfeitoria | G18: =G15*G16*G5 -> 262500
B19: FC | C19: 1 | D19: =C18*C19 -> 770833.33 | H19: =G18*C19 -> 262500
B20: Capital Imóvel | C20: =C19*(C18+G18) -> 1033333.3 | F20: qbo | G20: =G18/G5 -> 583.33333
B22: Taxas de rendimento
A23: Terreno | B23: Taxa básica | C23: 0.06 | E23: Benfeitorias | F23: Taxa básica | G23: 0.06
B24: Não liquidez | C24: 0.045 | F24: Não liquidez | G24: 0.01
B25: Valorização do Capital | C25: -0.015 | F25: Depreciação | G25: 0.01
F26: Vacância | G26: 0.01
B27: it | C27: =SUM(C23:C25) -> 0.09 | F27: ib | G27: =SUM(G23:G26) -> 0.09
B29: Cota Parte | D29: Ctu | E29: Cbu | F29: Valor Locativo | G29: VU | H29: d
B30: Térreo | C30: =J10/J12 -> 0.55675676 | D30: =C30*$D$19 -> 429166.67 | E30: =G3*$G$15*$G$16*$C$19 -> 87500 | F30: =(D30*C27+E30*G27)/12 -> 3875 | G30: =F30/G3 -> 25.833333 | H30: =G30/G31 -> 2
B31: Superiores | C31: =J11/J12 -> 0.44324324 | D31: =C31*$D$19 -> 341666.67 | E31: =G4*$G$15*$G$16*$C$19 -> 175000 | F31: =(D31*C27+E31*G27)/12 -> 3875 | G31: =F31/G4 -> 12.916667
E32: TOTAL (R$/mês) | F32: =SUM(F30:F31) -> 7750
B34: Cálculo com taxa composta
B35: i | C35: =(C18*C27+G18*G27)/(C18+G18) -> 0.09
B36: Valor locativo | C36: =C20*C35/12 -> 7750

Sheet Cota Parte
B1: TO | C1: =CA!C7 -> 0.5 | E1: qb | F1: =CA!G15 -> 750 | H1: Idade | I1: =CA!F9 -> 10 | L1: Relação de aluguéis (térreo/superiores)
B2: CA básico | C2: =CA!C6 -> 1 | E2: Depreciação | F2: =CA!G16 -> 0.77777778 | H2: Vida Útil | I2: =CA!G9 -> 36 | L2: Peso d | M2: =I12/I13 -> 1.9117647
B3: qt | C3: =CA!C4 -> 2000 | E3: ib | F3: =CA!G27 -> 0.09 | L3: pcalculado | M3: =(F1*F2*(M2-1)*(C2-C1)+C3*M2)/(C3-F1*F2*(M2-1)*C1) -> 2.3583039
B4: At | C4: =CA!C3 -> 400
B5: it | C5: =CA!C27 -> 0.09 | E5: FC | F5: =CA!C19 -> 1
E6: Taxa Composta (i) | F6: =CA!C35 -> 0.09
B8: Os cálculos abaixo correm como se o avaliador não tivessem conhecimento algum a respeito da área do terreno e da área total dos pavimentos
B10: Tabela 1: Cálculo do valor locatício de cada andar em separado, sem fazer qualquer hipótese a respeito da composição da área total construída do edifício. | N10: Verificação
A11: Valor por andar | B11: Andar | C11: Área Construída | D11: Pesos | E11: Ah | F11: Fórmula Cota-Parte | G11: Capital Benfeitoria | H11: Valor Locativo | I11: Valor por m2 | J11: Taxa Composta | K11: VUvenda | M11: VUvenda | O11: VUaluguel
B12: Térreo | C12: =CA!G3 -> 150 | D12: =CA!J4 -> 2.5121951 | E12: =C12*D12 -> 376.82927 | F12: =$C$3*E12*(0.2+0.8*($I$2-$I$1)/$I$2)/($C$1*$D$12+($C$2-$C$1)*$D$13) -> 333796.3 | G12: =C12*$F$1*$F$2 -> 87500 | H12: =$F$5*(F12*$C$5+G12*$F$3)/12 -> 3159.7222 | I12: =H12/C12 -> 21.064815 | J12: =12*H12/(F12+G12) -> 0.09 | K12: =12*H12/(J12*C12) -> 2808.642 | M12: =(F12+G12)/C12 -> 2808.642 | N12: =IF(K12=M12,"OK!","ERRO!") -> OK! | O12: =K12*J12/12 -> 21.064815 | P12: =IF(I12=O12,"OK!","ERRO") -> OK!
B13: Superiores | C13: =CA!G4 -> 300 | D13: =CA!I11 -> 1 | E13: =C13*D13 -> 300 | F13: =$C$3*E13*(0.2+0.8*($I$2-$I$1)/$I$2)/($C$1*$D$12+($C$2-$C$1)*$D$13) -> 265740.74 | G13: =C13*$F$1*$F$2 -> 175000 | H13: =$F$5*(F13*$C$5+G13*$F$3)/12 -> 3305.5556 | I13: =H13/C13 -> 11.018519 | J13: =12*H13/(F13+G13) -> 0.09 | K13: =12*H13/(J13*C13) -> 1469.1358 | M13: =(F13+G13)/C13 -> 1469.1358 | N13: =IF(K13=M13,"OK!","ERRO!") -> OK! | O13: =K13*J13/12 -> 11.018519 | P13: =IF(I13=O13,"OK!","ERRO") -> OK!
B14: TOTAL | C14: =SUM(C12:C13) -> 450 | F14: =SUM(F12:F13) -> 599537.04 | G14: =SUM(G12:G13) -> 262500 | H14: =SUM(H12:H13) -> 6465.2778
B16: Tabela 2: Cálculo do valor locatício de uma loja, laje ou sala no edifício, sem fazer qualquer hipótese a respeito da composição da área total construída do edifício.
C17: Área Construída | D17: Pesos | E17: Ahu | F17: CTu | G17: Capital Benfeitoria | H17: Valor Locativo | I17: Valor por m2 | J17: Verificação
B18: 1. Loja (90 m2) | C18: 90 | D18: =D12 -> 2.5121951 | E18: =C18*D18 -> 226.09756 | F18: =$C$3*E18*(0.2+0.8*($I$2-$I$1)/$I$2)/($C$1*$D$12+($C$2-$C$1)*$D$13) -> 200277.78 | G18: =C18*$F$1*$F$2 -> 52500 | H18: =$F$5*(F18*$C$5+G18*$F$3)/12 -> 1895.8333 | I18: =H18/C18 -> 21.064815 | J18: =IF(I18=I12,"Ok!","ERRO") -> Ok! | L18: =C18/$C$12*$H$12 -> 1895.8333
B19: 2. Loja (60 m2) | C19: 60 | D19: =D12 -> 2.5121951 | E19: =C19*D19 -> 150.73171 | F19: =$C$3*E19*(0.2+0.8*($I$2-$I$1)/$I$2)/($C$1*$D$12+($C$2-$C$1)*$D$13) -> 133518.52 | G19: =C19*$F$1*$F$2 -> 35000 | H19: =$F$5*(F19*$C$5+G19*$F$3)/12 -> 1263.8889 | I19: =H19/C19 -> 21.064815 | L19: =C19/$C$12*$H$12 -> 1263.8889
B20: 3. Laje Corporativa (150 m2) | C20: 150 | D20: =D13 -> 1 | E20: =C20*D20 -> 150 | F20: =$C$3*E20*(0.2+0.8*($I$2-$I$1)/$I$2)/($C$1*$D$12+($C$2-$C$1)*$D$13) -> 132870.37 | G20: =C20*$F$1*$F$2 -> 87500 | H20: =$F$5*(F20*$C$5+G20*$F$3)/12 -> 1652.7778 | I20: =H20/C20 -> 11.018519 | J20: =IF(I20=I13,"Ok!","ERRO") -> Ok! | L20: =C20/$C$13*$H$13 -> 1652.7778
B21: 4. Sala Comercial (60 m2) | C21: 60 | D21: =D13 -> 1 | E21: =C21*D21 -> 60 | F21: =$C$3*E21*(0.2+0.8*($I$2-$I$1)/$I$2)/($C$1*$D$12+($C$2-$C$1)*$D$13) -> 53148.148 | G21: =C21*$F$1*$F$2 -> 35000 | H21: =$F$5*(F21*$C$5+G21*$F$3)/12 -> 661.11111 | I21: =H21/C21 -> 11.018519 | L21: =C21/$C$13*$H$13 -> 661.11111
B22: 5. Sala Comercial (90 m2) | C22: 90 | D22: =D13 -> 1 | E22: =C22*D22 -> 90 | F22: =$C$3*E22*(0.2+0.8*($I$2-$I$1)/$I$2)/($C$1*$D$12+($C$2-$C$1)*$D$13) -> 79722.222 | G22: =C22*$F$1*$F$2 -> 52500 | H22: =$F$5*(F22*$C$5+G22*$F$3)/12 -> 991.66667 | I22: =H22/C22 -> 11.018519 | L22: =C22/$C$13*$H$13 -> 991.66667
F23: =SUM(F18:F22) -> 599537.04 | G23: =SUM(G18:G22) -> 262500 | H23: =SUM(H18:H22) -> 6465.2778
